endpoints/sfx.py
endpoints/tts.py
endpoints/users.py
ganai-0.1.2.dist-info/METADATA
ganai-0.1.2.dist-info/WHEEL
ganai-0.1.2.dist-info/entry_points.txt
ganai-0.1.2.dist-info/top_level.txt
ganai-0.1.2.dist-info/RECORD
