Metadata-Version: 2.4
Name: GanAI
Version: 0.1.2
Summary: Gan AI API wrapper
Author-email: sachin <sachin@gan.studio>
License-Expression: MIT
Requires-Python: >=3.12
Requires-Dist: requests
Requires-Dist: typer
